sbmutils/__init__.py
sbmutils/decomp/__init__.py
sbmutils/decomp/nmf.py
sbmutils/preprocess/__init__.py
sbmutils/preprocess/bio_normalization.py
sbmutils/preprocess/filter.py
sbmutils/preprocess/normalization.py
sbmutils/stat/__init__.py
sbmutils-0.2.3.dist-info/LICENSE
sbmutils-0.2.3.dist-info/METADATA
sbmutils-0.2.3.dist-info/WHEEL
sbmutils-0.2.3.dist-info/top_level.txt
sbmutils-0.2.3.dist-info/RECORD
