Metadata-Version: 2.2
Name: sbmutils
Version: 0.2.3
Summary: A collection of SBM utility functions
Home-page: https://github.com/dalee/sbmutils
Author: dalee
Classifier: Programming Language :: Python :: 3
Classifier: License :: OSI Approved :: MIT License
Classifier: Operating System :: OS Independent
Requires-Python: >=3.6
License-File: LICENSE
Requires-Dist: numpy
Requires-Dist: scipy
Requires-Dist: inmoose
Requires-Dist: pyranges
Requires-Dist: gtfparse
Requires-Dist: pybiomart
Provides-Extra: dev
Requires-Dist: pytest>=7.0.0; extra == "dev"
Dynamic: author
Dynamic: classifier
Dynamic: description
Dynamic: description-content-type
Dynamic: home-page
Dynamic: provides-extra
Dynamic: requires-dist
Dynamic: requires-python
Dynamic: summary
